subdivision_smoothing/__init__.py
subdivision_smoothing/geometry.py
subdivision_smoothing-0.1.5.dist-info/METADATA
subdivision_smoothing-0.1.5.dist-info/WHEEL
subdivision_smoothing-0.1.5.dist-info/licenses/LICENSE
subdivision_smoothing-0.1.5.dist-info/RECORD
